{
  "ANIMATION": {
    "HEADER": "Character Animation",
    "NAMES": [
      "Julio Duque Montero",
      "Jon Sandler"
    ]
  },
  "DEV": {
    "HEADER": "Development & Design",
    "NAMES": [
      "Anthony Giovannetti",
      "Casey Yano"
    ]
  },
  "ILLUSTRATION": {
    "HEADER": "Promo & Background Illustration",
    "NAMES": [
      "Bruce Brenneise"
    ]
  },
  "LOC_ADDITIONAL": {
    "HEADER": "Additional Translations",
    "NAMES": [
      "MoGi Group"
    ]
  },
  "LOC_CAT": {
    "HEADER": "Catalan Localization",
    "NAMES": [
    ]
  },
  "LOC_DEU": {
    "HEADER": "German Localization",
    "NAMES": [
      "Joshua \"Joshipon\" Wiegand",
      "Dustin \"Skrelpoid\" Kristen",
      "Christoph \"Deknud\" Hartmann",
      "Jonas Trodler",
      "Hongkong Koma",
      "Moly",
      "koykoy13",
      "Magnus Upmann"
    ]
  },
  "LOC_DUT": {
    "HEADER": "Dutch Localization",
    "NAMES": [
      "Gremlin Leader:",
      "Jelle Steinmann \"NotADitto\"",
      "Gremlin Nob:",
      "Charlie \"Alcus\" Ye",
      "Gremlins:",
      "Oscar Cousin",
      "\"Meriscan\"",
      "Lise Leitner",
      "Joris \"Mort\" Bogers"
    ]
  },
  "LOC_EPO": {
    "HEADER": "Esperanto Localization",
    "NAMES": [
      "Vincent \"Babelismoj\" Oostelbos",
      "Spencer van der Meulen"
    ]
  },
  "LOC_FIN": {
    "HEADER": "Finnish Localization",
    "NAMES": [
      "jahasjahas",
      "Juhana Uuttu",
      "Murasaki#6571",
      "Zalminen"
    ]
  },
  "LOC_FRA": {
    "HEADER": "French Localization",
    "NAMES": [
      "Xavier \"Blagatt\" Dupont",
      "Malik \"Devexia\" Leonarski",
      "Thomas \"Elgerine\" Ferry",
      "Vincent \"Henip\" Bartoux",
      "Alexandre \"Judgy\" Gaubert",
      "Vincent \"MissingNoShiny\" Larcin",
      "Nicky \"Qazahar\" Dehout",
      "Julien \"RoPeTTe\" Ropero",
      "Boby \"Tagada\" Vurpillot",
      "Corentin \"Tchus\" Monfort",
      "Zachary \"WyvernZed\" Janisse"
    ]
  },
  "LOC_GRE": {
    "HEADER": "Greek Localization",
    "NAMES": [
      "Kotsos \"Iglor\" Diamond"
    ]
  },
  "LOC_IND": {
    "HEADER": "Indonesian Localization",
    "NAMES": [
      "Aditya \"RiSQ.\" Arifin",
      "Daryan \"Samus\" Ramadhany",
      "Haveiszal \"Szaal\" Faroqie",
      "Jason Julian"
    ]
  },
  "LOC_ITA": {
    "HEADER": "Italian Localization",
    "NAMES": [
      "Jade \"HobNob\" Stevanovic",
      "Mero Marco",
      "Luigi Squarzina",
      "Playtesting:",
      "Mattylink Heropon"
    ]
  },
  "LOC_JPN": {
    "HEADER": "Japanese Localization",
    "NAMES": [
      "Grezzz (Community Translation)",
      "Kakehashi Games (Official Translation)"
    ]
  },
  "LOC_KOR": {
    "HEADER": "Korean Localization",
    "NAMES": [
      "Translation and Coordination:",
      "Eteriny",
      "Fissh",
      "GyeRyak",
      "Translation:",
      "Simcoding",
      "DesFrog",
      "insight",
      "K4lium",
      "hina",
      "Vekan",
      "Font:",
      "In-Game: GyeonggiCheonnyeon(Batang) by Gyeonggi-Do",
      "Shop Asset: NanumBrush, NanumPen by NAVER Corporation"
    ]
  },
  "LOC_NOR": {
    "HEADER": "Norwegian Localization",
    "NAMES": [
      "Eystein Jarp"
    ]
  },
  "LOC_POL": {
    "HEADER": "Polish Localization",
    "NAMES": [
      "Translation and Coordination:",
      "Stanisław \"ST4H\" Borkowski",
      "Oskar \"volf3n\" Nowak",
      "Additional Translations:",
      "Adrian \"xeros\" Rolka",
      "Marek \"Skorpionex\" Mazur",
      "Foreigner",
      "Proofreading:",
      "Oskar \"volf3n\" Nowak",
      "Suggestions and Feedback:",
      "Kasper \"Awokado\" Berc",
      "Paweł \"BASTIL\" Kaleta",
      "Grzegorz \"GregPL\" Bogusławski",
      "Erwin \"mateusz3010\" Matys",
      "Mettie",
      "Rafał \"SponTon83\" Szyszko"
    ]
  },
  "LOC_PTB": {
    "HEADER": "Brazilian-Portuguese Localization",
    "NAMES": [
      "Guilherme \"GPerego\" Perego",
      "Gustavo \"KomKlave\" Duarte",
      "José \"Maneimax\" Vasconcelos",
      "Leonardo \"Iikat\" Takii",
      "Nathan \"NoxShadow\" Cervieri",
      "Paulo \"SilverTape\" Hauck"
    ]
  },
  "LOC_RUS": {
    "HEADER": "Russian Localization",
    "NAMES": [
      "Translation:",
      "Ivan \"Ingrett\" Khoroshunenko",
      "Vladislav \"Vlad-00003\" Bolshakov",
      "Dmitry \"Regallion\" Zhiryakov",
      "Additional Translation:",
      "Dmitry \"Gentle Giant\" Gitsman",
      "Neprim",
      "Mikhail \"Outmind\" Dyuzhev",
      "Bohdan \"DarkRosse\" Kalytiuk",
      "Sergey \"lol10801lol\" K.",
      "Ascimator",
      "Kateryna \"Meds\" Belimenko-Bolger",
      "Alexey \"Surrealistic Ganerson\" Popov",
      "Alexandr \"LiaNdrY\" Mazistov",
      "Shop Asset Translation:",
      "Urist McFerrum"
    ]
  },
  "LOC_SPA": {
    "HEADER": "Spanish Localization",
    "NAMES": [
      "Translation and Coordination:",
      "Juanjo \"ajuanjojjj\" Martinez",
      "Pedro Luis \"PerikiyoXD\" Valadés Viera",
      "Translation:",
      "Erick Marroquin",
      "Accord",
      "Xavier \"xabad98\" Abad Salinas",
      "Sergio \"Skiddome\" Malagón",
      "Pedro J. \"PJJLegend\" Jiménez Moyano",
      "Rodrigo \"skylex\" Zabattaro",
      "Alberto \"RadeonThe1st\" Botana",
      "Spooktacular",
      "Grammar and Cleanup:",
      "Joaquín \"Pip1n\" López",
      "Xavier Castañer",
      "Summer",
      "Eipic"
    ]
  },
  "LOC_SRB": {
    "HEADER": "Serbian Localization",
    "NAMES": [
      "Nikola \"hauzer\" Vukosavljevic"
    ]
  },
  "LOC_THA": {
    "HEADER": "Thai Localization",
    "NAMES": [
      "Translation and Coordination:",
      "Noppon Varapaiboon (PlearnGaming)",
      "Additional Translations:",
      "Rapeepat Suwan (Yuu)",
      "Sarawut Suwan (Tomoeic)",
      "Fonts:",
      "CSChatThaiUI by raveetavan@gmail.com",
      "Layiji MaHaNiYom by layiji@gmail.com"
    ]
  },
  "LOC_TUR": {
    "HEADER": "Turkish Localization",
    "NAMES": [
      "Translation and Coordination:",
      "Ertürk Yılmaz",
      "Translation:",
      "Erdem Gürbüz",
      "Ege \"sLanKy\" Güçkıran",
      "\"onparalelkenarag\"",
      "Berkan Çalıkoğlu"
    ]
  },
  "LOC_UKR": {
    "HEADER": "Ukrainian Localization",
    "NAMES": [
      "Translation and Coordination:",
      "Vladyslav \"DarkXylese\" Kashtelyanov",
      "Corrections and Translation:",
      "Vasyl \"RDSk\" Mykhaliuk",
      "Artem \"Crazytosik\" Zemlianyi",
      "Dariia \"Dariianity\" Porechna"
    ]
  },
  "LOC_VIE": {
    "HEADER": "Vietnamese Localization",
    "NAMES": [
      "MercTrans Localization Team",
      "Translation:",
      "Dinh Long Hoang (donkrieg1011)",
      "Dinh Hoang Nguyen (clesta)",
      "Coordination and Linguistic Lead:",
      "Hoang Son Do",
      "Special Thanks:",
      "Azy Tazer"
    ]
  },
  "LOC_ZHS": {
    "HEADER": "Chinese (Simplified) Localization",
    "NAMES": [
      "Sound of Mystery",
      "IrisRaphael"
    ]
  },
  "LOC_ZHT": {
    "HEADER": "Chinese (Traditional) Localization",
    "NAMES": [
      "professor",
      "bowans",
      "Angryfox"
    ]
  },
  "OPS": {
    "HEADER": "Operations & Metrics",
    "NAMES": [
      "Danielle Jenkins",
      "Jake Rabinowitz"
    ]
  },
  "PORTING": {
    "HEADER": "Console and Mobile Ports",
    "NAMES": [
      "Sickhead Games, LLC"
    ]
  },
  "PORTRAITS": {
    "HEADER": "Card Portraits & Event Art",
    "NAMES": [
      "Anailis Dorta"
    ]
  },
  "PUBLISHING": {
    "HEADER": "Humble Bundle",
    "NAMES": [
      "GM:  Alan Patmore",
      "CBO:  Steven Kovensky",
      "VP, Business Development:  Eduardo Aparicio",
      "Publishing Manager:  John Polson",
      "Publishing Release Manager: Evan Koepf",
      "Publishing Brand Manager:  Connor Bridgeman",
      "Business Development Director, Publishing:  Mai Kawaguchi",
      "Senior Business Developer:  Thomas Glenn",
      "Senior Business Developer:  Bob Mills",
      "Business Developer:  Trisha Tabor",
      "Business Developer:  Angel Lyons-Labate",
      "Store Director:  Paul Herron",
      "Director of Finance:  Eric Samuel",
      "VP of Product:  Nate Muller",
      "Director of Marketing:  Jeremie Vella",
      "Marketing Manager:  Whitney Stutes",
      "Marketing Growth Manager:  Francois du Toit",
      "Ninja Support:  Jimmy Chi",
      "Ninja Support:  Kasey Brounkowski",
      "Ninja Support:  Kayla Fyfe",
      "Ninja Support:  Patrick Monahan"
    ]
  },
  "SOUND": {
    "HEADER": "Music & Sounds",
    "NAMES": [
      "Clark Aboud"
    ]
  },
  "SPECIAL": {
    "HEADER": "Special Thanks",
    "NAMES": [
      "Harry Rabinowitz",
      "Kevin \"Billy\" Matheson",
      "Anthony Roybal",
      "Lee Beckman",
      "Sam Welch",
      "feedbackbot",
      "Evan Howell",
      "Justin Myhres",
      "robojumper",
      "Tony \"kiooeht\" Moore",
      "John Vega",
      "Steve Groll",
      "Sara Popescu",
      "Ryan Hamann"
    ]
  },
  "TEST": {
    "HEADER": "Playtesters",
    "NAMES": [
      "Agari",
      "Daria Anderson",
      "Zac Bauermeister",
      "Nick Becker",
      "Esther Beckman",
      "Leo Chen",
      "Brian Chau",
      "Dan D'Argenio",
      "David Delorenzo",
      "Tim Erskine",
      "Benjamin Finkel",
      "Rajiv Giridharagopal",
      "Wyatt Grodzins",
      "Ren Howell",
      "Kyle James",
      "Ryan Mathisen",
      "Anthony McMillian",
      "Brad Meine",
      "Jade Wesley",
      "Alex Rockwell",
      "Greg Scheopner",
      "John \"Slide20xl\" Smith",
      "Aaron Taggart",
      "Alexander Toy",
      "Merijn van der Vliet",
      "David Von Derau",
      "Conor Watson",
      "David \"divadus\" Withington",
      "Jason \"Wyrm\" Deng",
      "Jonas \"bigunit3000\" Wilson",
      "TBytemaster"
    ]
  },
  "THANKS_MSG": {
    "HEADER": "...and thank YOU for playing!",
    "NAMES": []
  },
  "VOICE": {
    "HEADER": "Voice Talent",
    "NAMES": [
      "Tamara Ryan",
      "Michael Schwalbe"
    ]
  },
  "KAKEHASHI": {
    "HEADER": "Kakehashi Games",
    "NAMES": [
      "Kakehashi Games (Official Translation):",
      "Japanese Publishing Support:  Kakehashi Games",
      "Japanese Localization:  Rie Ihara"
    ]
  }
}
